README
setup.py
src/basecampreporting/__init__.py
src/basecampreporting/basecamp.py
src/basecampreporting/etree.py
src/basecampreporting/mocks.py
src/basecampreporting/parser.py
src/basecampreporting/project.py
src/basecampreporting/sample.py
src/basecampreporting/serialization.py
src/basecampreporting.egg-info/PKG-INFO
src/basecampreporting.egg-info/SOURCES.txt
src/basecampreporting.egg-info/dependency_links.txt
src/basecampreporting.egg-info/requires.txt
src/basecampreporting.egg-info/top_level.txt
src/basecampreporting/tests/__init__.py
src/basecampreporting/tests/test_parser.py
src/basecampreporting/tests/test_project.py
src/basecampreporting/tests/test_serialization.py